sendbird_platform_sdk/__init__.py
sendbird_platform_sdk/api_client.py
sendbird_platform_sdk/configuration.py
sendbird_platform_sdk/exceptions.py
sendbird_platform_sdk/model_utils.py
sendbird_platform_sdk/rest.py
sendbird_platform_sdk/api/__init__.py
sendbird_platform_sdk/api/announcement_api.py
sendbird_platform_sdk/api/bot_api.py
sendbird_platform_sdk/api/group_channel_api.py
sendbird_platform_sdk/api/message_api.py
sendbird_platform_sdk/api/metadata_api.py
sendbird_platform_sdk/api/moderation_api.py
sendbird_platform_sdk/api/open_channel_api.py
sendbird_platform_sdk/api/statistics_api.py
sendbird_platform_sdk/api/user_api.py
sendbird_platform_sdk/apis/__init__.py
sendbird_platform_sdk/model/__init__.py
sendbird_platform_sdk/model/accept_an_invitation_request.py
sendbird_platform_sdk/model/accept_an_invitation_response.py
sendbird_platform_sdk/model/add_a_registration_or_device_token_request.py
sendbird_platform_sdk/model/add_a_registration_or_device_token_response.py
sendbird_platform_sdk/model/add_extra_data_to_a_message_request.py
sendbird_platform_sdk/model/add_extra_data_to_a_message_response.py
sendbird_platform_sdk/model/block_a_user_request.py
sendbird_platform_sdk/model/block_a_user_response.py
sendbird_platform_sdk/model/check_if_member_response.py
sendbird_platform_sdk/model/choose_a_push_notification_content_template_request.py
sendbird_platform_sdk/model/choose_a_push_notification_content_template_response.py
sendbird_platform_sdk/model/create_a_bot_request.py
sendbird_platform_sdk/model/create_a_bot_response.py
sendbird_platform_sdk/model/create_a_bot_response_bot.py
sendbird_platform_sdk/model/create_a_channel_metadata_request.py
sendbird_platform_sdk/model/create_a_channel_metadata_response.py
sendbird_platform_sdk/model/create_a_group_channel_request.py
sendbird_platform_sdk/model/create_a_group_channel_response.py
sendbird_platform_sdk/model/create_a_user_request.py
sendbird_platform_sdk/model/create_a_user_response.py
sendbird_platform_sdk-2.1.2.dist-info/METADATA
sendbird_platform_sdk-2.1.2.dist-info/WHEEL
sendbird_platform_sdk-2.1.2.dist-info/top_level.txt
sendbird_platform_sdk-2.1.2.dist-info/RECORD
