Metadata-Version: 2.1
Name: sendbird-platform-sdk
Version: 2.1.2
Summary: Sendbird Platform SDK
Home-page: UNKNOWN
Author: Sendbird
Author-email: support@sendbird.com
License: UNKNOWN
Keywords: OpenAPI,OpenAPI-Generator,Sendbird Platform SDK
Platform: UNKNOWN
Requires-Python: >=3.6
Requires-Dist: urllib3 (>=2.6.0)
Requires-Dist: python-dateutil
